Workbook

Sheet How to use this template

Sheet Cashflow
A1: Monthly Cash Flow Summary – (Your Name)
A2: =TODAY() -> 44209 | B2: =TODAY() -> 44209 | C2: =TODAY() -> 44209
A5: Monthly Income Sources | B5: Monthly | C5: Totals
A6: Revenue property rental income | B6: ='Real Estate Balance Sheet'!E38 -> 0
A7: Employment or business income | B7: 0
A8: Other Income: | B8: 0
A9: Other Income: | B9: 0
A10: Total Income Per Month | C10: =SUM(B6:B9) -> 0
A12: EXPENSES
A13: Regular Monthly Expenses | B13: Monthly | C13: Totals
A14: Revenue property debt servicing and all other expenses (See Appendix C) | B14: ='Overview Rentals'!F26+'Overview Rentals'!G26 -> 0
A15: Principle residence mortgage (rent or mortgage payments) (See Appendix D) | B15: ='Real Estate Balance Sheet'!H7 -> 0
A16: Utilities: heat, light, telephone, internet,alarm, cable, city tax | B16: 0
A17: Automobile transportation: gasoline, maintenance, parking | B17: 0
A18: Groceries and other household supplies | B18: 0
A19: Clothing: including work clothes, sportswear, repairs, accessories | B19: 0
A20: Life Insurance premiums | B20: 0
A21: Medical & Dental Care: including prescription drugs and deductible expenses | B21: 0
A22: Consumer Credit Payments: department store accounts, credit cards etc. | B22: 0
A23: Other Personal Spending: grooming aids, haircuts, dry-cleaning, etc. | B23: 0 | C23: =SUM(B14:B23) -> 0
A24: Discretionary Spending | B24: Monthly | C24: Totals
A25: Savings: retirement fund, vacation fund | B25: 0
A26: Educational Expenses: tuitions, books, materials | B26: 0
A27: Entertainment: dining, theatre tickets, printed materials, etc. | B27: 0
A28: Gifts: special occasions, charitable donations, etc. | B28: 0
A29: Miscellaneous: long-distance phone/fax calls, lunches & snacks, indulgences.... | B29: 0 | C29: =SUM(B25:B29) -> 0
A30: Occasional Expenses (including regular non-monthly payments) | B30: Annually | C30: Monthly
A31: Home Insurance: paid annually | B31: 0 | C31: =B31/12 -> 0
A32: Auto Insurance: paid annually | B32: 0 | C32: =B32/12 -> 0
A33: Recreational and/or club memberships: paid quarterly | B33: 0 | C33: =(B33*4)/12 -> 0
A34: Furniture & Appliance Purchases & Repairs: occasional expenses | B34: 0 | C34: =B34/12 -> 0
A35: Total Expenses Per Month | C35: =SUM(C29,C23,C31:C34) -> 0
A37: MONTHLY RESIDUAL INCOME: | B37: =C10-C35 -> 0

Sheet Balance Statement
A1: Balance Statement (Your Name)
A2: =TODAY() -> 44209
A4: ASSETS | D4: LIABILITIES | G4: INSURANCE
A6: Deposit Accounts (banks,trust co.'s, etc.) | D6: Mortgages | H6: Policy Number | I6: Sum Insured | J6: Total Less Loans
A7: Chequing/Savings Accounts (Appendix B) | B7: ='RRSP & Credit'!C60 -> 0 | D7: Rental Properties (See Appendix C) | E7: ='Real Estate Balance Sheet'!G38 -> 0 | G7: Name Insured
A8: Joint Accounts (Appendix B) | B8: ='RRSP & Credit'!C69 -> 0 | D8: Principle Residence (See Appendix D) | E8: ='Real Estate Balance Sheet'!G17 -> 0 | G8: Name Insured
A9: TOTAL Deposit Accounts | B9: =SUM(B7:B8) -> 0 | D9: TOTAL Mortgages | E9: =SUM(E7:E8) -> 0 | G9: Name Insured
G10: Name Insured
A11: Investments (registered & unregistered funds) | G11: Name Insured
A12: RRSP/Investment Portfolio (Appendix A) | B12: ='RRSP & Credit'!D22 -> 0 | D12: Consumer Loans (Appendix B) | G12: Name Insured
A13: Life Insurance | B13: =SUM(J7:J13) -> 0 | D13: TOTAL Loans, Lines of Credit | E13: ='RRSP & Credit'!C39 -> 0
A14: TOTAL Investments | B14: =SUM(B12:B13) -> 0
A16: Real Estate Portfolio | D16: Accounts Payable (See Appendix B)
A17: Rental Property Portfolio (Appendix C) | B17: ='Overview Rentals'!D26 -> 0 | D17: TOTAL Accounts Payable | E17: ='RRSP & Credit'!C47 -> 0
A18: Principal Residence and other property (Appendix D) | B18: ='Real Estate Balance Sheet'!D17 -> 500000
A19: TOTAL Real Estate Portfolio | B19: =(B17+B18) -> 500000
A21: Goods and Chattels
A22: Gold, Silver, Diamonds, Jewelry | B22: 0
A23: Antiques | B23: 0
A24: Vehicle 1 | B24: 0
A25: Vehicle 2 | B25: 0
A26: Furniture & Appliances | B26: 0
A27: Business Equipment | B27: 0
A28: Electronics | B28: 0
B31: 0
A32: TOTAL Goods and Chattels | B32: =SUM(B22:B31) -> 0
A34: TOTAL ASSETS | B34: =B9+B14+B32+B19 -> 500000 | D34: TOTAL LIABILITIES | E34: =E17+E13+E9 -> 0
A36: Net Worth | B36: =B34-E34 -> 500000

Sheet RRSP & Credit
A1: Appendix A
A2: RRSP / RRIF / Investment Portfolio of (Your Name)
A3: =TODAY() -> 44209
A5: Mutual Funds, RRSP’s / RRIF’s, Stocks, Bonds, GIC's | B5: Account Num | C5: Date of Last Statement | F5: Share Price | G5: Num of Shares
A22: TOTAL Mutual Fund RRSP’s / RRIF’s | D22: =SUM(D6:D21) -> 0
A25: Appendix B
A26: Credit Status
A27: =TODAY() -> 44209
B29: Monthly | C29: Current | D29: Funds | F29: Credit Limit | G29: Min Pymt
A30: Lines of Credit, Personal Loans: | B30: Payments | C30: Balance | D30: Available
B31: =(C31*G31)/12 -> 0 | D31: =F31-C31 -> 0 | G31: 0.04
B32: =(C32*G32)/12 -> 0 | D32: =F32-C32 -> 0 | G32: 0.08
B36: 0 | C36: 0 | D36: 0
B38: 0 | C38: 0 | D38: 0
A39: TOTAL for Lines of Credit | B39: =SUM(B31:B38) -> 0 | C39: =SUM(C31:C38) -> 0 | D39: =SUM(D31:D38) -> 0
A41: Credit Cards | F41: Credit Limit
D42: =F42-C42 -> 0 | F42: 0
D43: =F43-C43 -> 0 | F43: 0
B44: 0 | D44: =F44-C44 -> 0 | F44: 0
F45: 0
B46: 0 | C46: 0 | D46: 0
A47: TOTALS for Credit Cards | B47: =SUM(B42:B46) -> 0 | C47: =SUM(C42:C46) -> 0 | D47: =SUM(D42:D46) -> 0
A49: Chequing/Savings Accounts
D50: 0
D52: 0
D53: 0
D59: 0
A60: TOTALS for Chequing/Savings Accounts | C60: =SUM(C49:C59) -> 0 | D60: =SUM(D49:D59) -> 0
A62: Joint Chequing/Savings Accounts
D63: 0
C68: 0
A69: TOTALS for Joint Chequing/Savings Accounts | C69: =SUM(C63:C68) -> 0 | D69: =SUM(D63:D68) -> 0
A71: Totals for Credit Status | B71: =B39+B47+B60 -> 0 | C71: =-C39-C47+C60+C69 -> 0 | D71: =D39+D47+D60+D69 -> 0

Sheet Overview Rentals
A2: Appendix C: Overview of Rental Properties (Your Name)
A3: =TODAY() -> 44209
C5: Year | D5: Current | E5: Mortgage | F5: Mortgage | G5: Taxes | H5: Rental
A6: # | B6: Property Address & Mortgage Information: | C6: Purch | D6: Value | E6: Balance | F6: Payment | G6: (Monthly) | H6: Income
A7: 1 | B7: ='Real Estate Balance Sheet'!B20 -> Rental Property Address 1 | D7: ='Real Estate Balance Sheet'!D20 -> 0 | E7: ='Real Estate Balance Sheet'!G20 -> 0 | F7: ='Real Estate Balance Sheet'!H20 -> 0 | H7: ='Real Estate Balance Sheet'!E20 -> 0
B8: ='Real Estate Balance Sheet'!B21 -> 0
A9: 2 | B9: ='Real Estate Balance Sheet'!B22 -> 0 | D9: ='Real Estate Balance Sheet'!D22 -> 0 | E9: ='Real Estate Balance Sheet'!G22 -> 0 | F9: ='Real Estate Balance Sheet'!H22 -> 0 | H9: ='Real Estate Balance Sheet'!E22 -> 0 | J9: (divide total tax by 12)
B10: ='Real Estate Balance Sheet'!B23 -> 0
A11: 3 | B11: ='Real Estate Balance Sheet'!B24 -> 0 | E11: ='Real Estate Balance Sheet'!G24 -> 0 | F11: ='Real Estate Balance Sheet'!H24 -> 0 | H11: ='Real Estate Balance Sheet'!E24 -> 0 | J11: (divide total tax by 12)
B12: ='Real Estate Balance Sheet'!B25 -> 0
A13: 4 | B13: ='Real Estate Balance Sheet'!B26 -> 0 | D13: ='Real Estate Balance Sheet'!D26 -> 0 | E13: ='Real Estate Balance Sheet'!G26 -> 0 | F13: ='Real Estate Balance Sheet'!H26 -> 0 | H13: ='Real Estate Balance Sheet'!E26 -> 0
B14: ='Real Estate Balance Sheet'!B27 -> 0
A15: 5 | B15: ='Real Estate Balance Sheet'!B28 -> 0 | D15: ='Real Estate Balance Sheet'!D28 -> 0 | E15: ='Real Estate Balance Sheet'!G28 -> 0 | F15: ='Real Estate Balance Sheet'!H28 -> 0 | H15: ='Real Estate Balance Sheet'!E28 -> 0 | J15: (divide total tax by 12)
B16: ='Real Estate Balance Sheet'!B29 -> 0
A17: 6 | B17: ='Real Estate Balance Sheet'!B30 -> 0 | D17: ='Real Estate Balance Sheet'!D30 -> 0 | E17: ='Real Estate Balance Sheet'!G30 -> 0 | F17: ='Real Estate Balance Sheet'!H30 -> 0 | H17: ='Real Estate Balance Sheet'!E30 -> 0
B18: ='Real Estate Balance Sheet'!B31 -> 0
A19: 7 | B19: ='Real Estate Balance Sheet'!B32 -> 0 | D19: ='Real Estate Balance Sheet'!D32 -> 0 | E19: ='Real Estate Balance Sheet'!G32 -> 0 | F19: ='Real Estate Balance Sheet'!H32 -> 0 | G19: 0 | H19: ='Real Estate Balance Sheet'!E32 -> 0
B20: ='Real Estate Balance Sheet'!B33 -> 0
A21: 8 | B21: ='Real Estate Balance Sheet'!B34 -> 0 | D21: ='Real Estate Balance Sheet'!D34 -> 0 | E21: ='Real Estate Balance Sheet'!G34 -> 0 | F21: ='Real Estate Balance Sheet'!H34 -> 0 | G21: 0 | H21: ='Real Estate Balance Sheet'!E34 -> 0
B22: ='Real Estate Balance Sheet'!B35 -> 0
A23: 9 | B23: ='Real Estate Balance Sheet'!B36 -> 0 | D23: ='Real Estate Balance Sheet'!D36 -> 0 | E23: ='Real Estate Balance Sheet'!G36 -> 0 | F23: ='Real Estate Balance Sheet'!H36 -> 0 | G23: 0 | H23: ='Real Estate Balance Sheet'!E36 -> 0
B24: ='Real Estate Balance Sheet'!B37 -> 0
B26: TOTALS FOR ALL REVENUE PROPERTIES | D26: =SUM(D7:D25) -> 0 | E26: =SUM(E7:E25) -> 0 | F26: =SUM(F7:F25) -> 0 | G26: =SUM(G7:G25) -> 0 | H26: =SUM(H7:H25) -> 0

Sheet Real Estate Balance Sheet
A1: Appendix D: Real Estate Assets and Liabilities
A2: =TODAY() -> 44209
B4: Real Estate Assets | G4: Real Estate Liabilities
A6: # | B6: Personal Properties: | C6: Equity | D6: Current Value | E6: Rent | G6: Mortgage Balance | H6: Monthly Pmt. | I6: Loan to Value
A7: 1 | B7: Principle Residence: your address | C7: =D7-G7 -> 500000 | D7: 500000 | E7: 0 | G7: 0 | H7: 0 | I7: =G7/D7 -> 0
A9: 2 | C9: 0 | D9: 0 | E9: 0 | G9: 0 | H9: 0 | I9: =G9/D9 -> #DIV/0!
A11: 3 | C11: =D11-G11 -> 0 | I11: =G11/D11 -> #DIV/0!
A13: 4 | C13: =D13-G13 -> 0 | I13: =G13/D13 -> #DIV/0!
A15: 5 | C15: =D15-G15 -> 0 | I15: =G15/D15 -> #DIV/0!
B17: Total Personal Real Estate Owned | C17: =SUM(C7:C16) -> 500000 | D17: =SUM(D7:D16) -> 500000 | E17: =SUM(E7:E16) -> 0 | G17: =SUM(G7:G16) -> 0 | H17: =SUM(H7:H16) -> 0 | I17: =G17/D17 -> 0
B19: Rental Properties:
A20: 1 | B20: Rental Property Address 1 | C20: =D20-G20 -> 0 | I20: =G20/D20 -> #DIV/0!
A22: 2 | C22: =D22-G22 -> 0 | I22: =G22/D22 -> #DIV/0!
A24: 3 | C24: =D24-G24 -> 0 | I24: =G24/D24 -> #DIV/0!
A26: 4 | C26: =D26-G26 -> 0 | I26: =G26/D26 -> #DIV/0!
A28: 5 | C28: =D28-G28 -> 0 | I28: =G28/D28 -> #DIV/0!
A30: 6 | C30: =D30-G30 -> 0 | I30: =G30/D30 -> #DIV/0!
A32: 7 | C32: =D32-G32 -> 0 | I32: =G32/D32 -> #DIV/0!
A34: 8 | C34: =D34-G34 -> 0 | I34: =G34/D34 -> #DIV/0!
D35: 0 | E35: 0 | G35: 0 | H35: 0
A36: 9 | C36: =D36-G36 -> 0 | I36: =G36/D36 -> #DIV/0!
D37: 0 | E37: 0 | G37: 0 | H37: 0
B38: Total Rental Property | C38: =SUM(C20:C37) -> 0 | D38: =SUM(D20:D37) -> 0 | E38: =SUM(E20:E37) -> 0 | G38: =SUM(G20:G37) -> 0 | H38: =SUM(H20:H37) -> 0 | I38: =G38/D38 -> #DIV/0!
B40: Totals for all Real Estate | C40: =C38+C17 -> 500000 | D40: =D38+D17 -> 500000 | E40: =E38+E17 -> 0 | G40: =G38+G17 -> 0 | H40: =H38+H17 -> 0 | I40: =G40/D40 -> 0

Sheet Sheet9

Sheet Sheet8

Sheet Sheet7

Sheet Sheet6

Sheet Sheet5
