Workbook

Sheet How to use this tool
A1: Cash Flow Analyser Overview
A3: Welcome to the Real Property Investments Cash Flow Analyser tool. This tool is provided as is. While every effort has gone into making it flawless, we have left cells open that could jeopardize certain formulas resulting in you experiencing some issues. Please keep this in mind as you assess your properties. There are several steps required to generate the Income & Expense Statement, the Financial Overview and the Cash Requirements. Follow the steps provided below and you will be ready to assess your properties like a professional!
E5: The Income and Expense sheet is your first tab.
E6: Operating Income 1. Populate the address 2. Enter your Gross expected income including the number of Commercial Units or Residential units there are, the expected monthly average income per unit and any services you offer. 3. Add your Vacancy/Bad Debt monthly reserve as a percentage for either the Commercial or Residential
E7: Operating Expenses 1. Complete all expenses associated with the property. There are additional Cells in case you have anything that's not listed. Place these in the "Other" rows and rename accordingly. 2. Add in a percentage for Maintenance and Management of the property. This will generate your Net Operating Income or NOI.
E30: The Financing Overview tab is next.
E32: Complete the Asking price, gross purchase price and abatement section. Next complete your financing options. This will generate your Total Yearly Payments which is used to generate your Coverage Ratio. A coverage ratio divides your income or cash flow by a certain expense in order to determine financial solvency. In general, coverage ratios equal to or greater than 1.0 indicate that you have enough earnings or cash to meet the obligation in question. Coverage ratios below 1.0 indicate that you may not be able to fulfill these obligations.
E44: Lastly is the Cash Requirements Tab
E46: In this tab you will enter in your Cash Requirements and fees.The spreadhseet will generate your Total Cash invested and the Total Closing Costs.
E48: You now have an overview of the property and an overview of all expenses vs income generating a snapshot of the property and if you are cashflow positive or not.

Sheet Income and Expense Statement
C1: Income and Expense Statement
A3: Operating Income
A5: Street Address: | B5: 123 Anywhere Ave
A6: City | B6: Overheresville
A7: Prov/State | B7: ON
A8: PC/ZIP | B8: H0H 0H0
A10: Gross Income: | B10: Commercial: | D10: Number of Units | E10: Monthly Avg per Unit
F11: =E11*D11*12 -> 0
D13: Number of Units | E13: Monthly Avg per Unit
B14: Residential: | C14: Rental | D14: 0 | F14: =D14*E14*12 -> 0
C15: Laundry Services | D15: 0 | F15: =D15*E15*12 -> 0
C16: Other Services | D16: 0 | F16: =D16*E16*12 -> 0
E18: Sub-Total Gross Income: | F18: =F11+F14+F15+F16 -> 0
A20: Less: | B20: Vacancy / Bad Debt - Commercial | D20: 0.05 | F20: =-(F11*D20) -> 0
B21: Vacancy / Bad Debt - Residential | D21: 0.03 | F21: =-(F18*D21) -> 0
A23: Effective Gross Income | F23: =F18+F20+F21 -> 0 | G23: 1
A25: Operating Expenses
E26: % of Revenue | F26: Yearly Total | G26: Per Unit/Month
C27: Taxes | E27: =F27/F23 -> #DIV/0! | F27: 0 | G27: =(F27/D14)/12 -> #DIV/0!
C28: Insurance | E28: =F28/F23 -> #DIV/0! | F28: 0 | G28: =(F28/D14)/12 -> #DIV/0!
C29: Water / Sewer | E29: =F29/F23 -> #DIV/0! | F29: 0 | G29: =(F29/D14)/12 -> #DIV/0!
C30: Electricity | E30: =F30/F23 -> #DIV/0! | F30: 0 | G30: =(F30/D14)/12 -> #DIV/0!
C31: Gas | E31: =F31/F23 -> #DIV/0! | F31: 0 | G31: =(F31/D14)/12 -> #DIV/0!
C32: Snow / Garbage | E32: =F32/F23 -> #DIV/0! | F32: 0 | G32: =(F32/D14)/12 -> #DIV/0!
C33: Other | E33: =F33/F23 -> #DIV/0! | F33: 0 | G33: =(F33/D14)/12 -> #DIV/0!
C34: Other | E34: =F34/F23 -> #DIV/0! | F34: 0 | G34: =(F34/D14)/12 -> #DIV/0!
C35: Other | E35: =F35/F23 -> #DIV/0! | F35: 0 | G35: =(F35/D14)/12 -> #DIV/0!
C36: Other | E36: =F36/F23 -> #DIV/0! | F36: 0 | G36: =(F36/D14)/12 -> #DIV/0!
C37: Other | E37: =F37/F23 -> #DIV/0! | F37: 0 | G37: =(F37/D14)/12 -> #DIV/0!
C38: Other | E38: =F38/F23 -> #DIV/0! | F38: 0 | G38: =(F38/D14)/12 -> #DIV/0!
C39: Other | E39: =F39/F23 -> #DIV/0! | F39: 0 | G39: =(F39/D14)/12 -> #DIV/0!
C40: Other | E40: =F40/F23 -> #DIV/0! | F40: 0 | G40: =(F40/D14)/12 -> #DIV/0!
C41: Sub-Total | E41: =F41/F23 -> #DIV/0! | F41: =SUM(F27:F40) -> 0 | G41: =(F41/D14)/12 -> #DIV/0!
C43: Maintenance | E43: 0.05 | F43: =E43*F23 -> 0 | G43: =(F43/D14)/12 -> #DIV/0!
C44: Management | E44: 0.05 | F44: =F23*E44 -> 0 | G44: =(F44/D14)/12 -> #DIV/0!
C45: Sub-Total | E45: =F45/F23 -> #DIV/0! | F45: =SUM(F43:F44) -> 0 | G45: =SUM(G43:G44) -> #DIV/0!
A48: Total Operating Expenses | F48: =F41+F45 -> 0 | G48: =F48/F23 -> #DIV/0!
A51: Net Operating Income (NOI) | F51: =F23-F48 -> 0 | G51: =F51/F23 -> #DIV/0!

Sheet Financing Overview
C1: Financing Overview
A3: FINANCING OVERVIEW
A6: Asking Price:
A7: Purchase Price:
A8: Abatment: | C8: 0
A9: Purchase Price: | C9: =C7-C8 -> 0 | E9: Price per unit: | F9: =C9/I9 -> #DIV/0! | H9: Number of Units: | I9: ='Income and Expense Statement'!D11+'Income and Expense Statement'!D14 -> 0
A10: Estimated Property Value: | C10: ='Income and Expense Statement'!F51/'Financing Overview'!C7 -> #DIV/0!
A11: [Based on a CapRate of 10%]
A13: Debt Service | B13: % | C13: Mortgage Amount | D13: Term | E13: Amortization Period | F13: Interest Rate | G13: Monthly Payment | H13: Yearly Total | I13: %
D14: (Month) | E14: (Year)
A16: First Mortgage | C16: =C9*B16 -> 0 | G16: =IF(E16>0,PMT(((1+(F16/200))^(1/6)-1),ABS(E16*12),-C16),0) -> 0 | H16: =G16*12 -> 0 | I16: =H16/'Income and Expense Statement'!F23 -> #DIV/0!
A17: Second Mortgage | C17: =B17*C9 -> 0 | G17: =IF(E17>0,PMT(((1+(F17/200))^(1/6)-1),ABS(E17*12),-C17),0) -> 0 | H17: =G17*12 -> 0 | I17: =H17/'Income and Expense Statement'!F23 -> #DIV/0!
A19: TOTAL | B19: =SUM(B16:B18) -> 0 | C19: =SUM(C16:C18) -> 0 | G19: =SUM(G16:G18) -> 0 | H19: =SUM(H16:H18) -> 0 | I19: =H19/'Income and Expense Statement'!F23 -> #DIV/0!
A21: PROMISSORY NOTE | B21: 0 | C21: 0 | D21: 0 | E21: 0 | F21: 0 | G21: =IF(E21>0,PMT(((1+(F21/200))^(1/6)-1),ABS(E21*12),-C21),0) -> 0 | H21: =G21*12 -> 0 | I21: =H21/'Income and Expense Statement'!F23 -> #DIV/0!
A23: CMHC | B23: 0 | C23: =C16*B23 -> 0 | D23: 0 | E23: =E16 -> 0 | F23: =F16 -> 0 | G23: =IF(E23>0,PMT(((1+(F23/200))^(1/6)-1),ABS(E23*12),-C23),0) -> 0 | H23: =G23*12 -> 0 | I23: =H23/'Income and Expense Statement'!F23 -> #DIV/0!
F24: Total Yearly Payment | H24: =SUM(H21,H19) -> 0
B27: Coverage Ratio
B29: Net Operating Income | E29: = | F29: ='Income and Expense Statement'!F51 -> 0 | G29: = | H29: =F29/F30 -> #DIV/0!
B30: Debt Service | F30: =H19+H21+H23 -> 0
A32: Cash Flow | H32: ='Income and Expense Statement'!F51-(H19+H21+H23) -> 0 | I32: =H32/'Income and Expense Statement'!F23 -> #DIV/0!

Sheet Cash Requirements
E1: Cash Requirements
B3: CASH REQUIREMENTS
C6: Total Downpayment: | E6: ='Financing Overview'!C9-'Financing Overview'!C16 -> 0 | G6: Closing / Acquisition Costs - Details
D8: 1st Deposit: | E8: 0 | G8: Lender's Fee (1st): | H8: 0 | I8: =H8/'Financing Overview'!$C$7 -> #DIV/0!
D9: 2nd Deposit: | E9: 0 | G9: CMHC Fee (1st): | H9: 0 | I9: =H9/'Financing Overview'!$C$7 -> #DIV/0!
D10: Abatment: | E10: ='Financing Overview'!C8 -> 0 | G10: Lender's Fee (2nd): | H10: 0 | I10: =H10/'Financing Overview'!$C$7 -> #DIV/0!
D11: Discount on Closing: | E11: 0 | G11: Legal Fee Lender (2nd): | H11: 0 | I11: =H11/'Financing Overview'!$C$7 -> #DIV/0!
D12: Cash Back: | E12: 0 | G12: Mortgage Broker Application: | H12: 0 | I12: =H12/'Financing Overview'!$C$7 -> #DIV/0!
D13: Promissory Note: | E13: ='Financing Overview'!C21 -> 0 | G13: Mortgage Broker's Fee: | H13: 0 | I13: =H13/'Financing Overview'!$C$7 -> #DIV/0!
D14: Balance on Closing: | E14: =E6-(SUM(E8:E13)) -> 0 | G14: Appraisal: | H14: 0 | I14: =H14/'Financing Overview'!$C$7 -> #DIV/0!
G15: Building Inspection: | H15: 0 | I15: =H15/'Financing Overview'!$C$7 -> #DIV/0!
D16: Cash Down Required: | E16: =E8+E9+E14 -> 0 | G16: Environmental Phase 1: | H16: 0 | I16: =H16/'Financing Overview'!$C$7 -> #DIV/0!
G17: Environmental Phase 2: | H17: 0 | I17: =H17/'Financing Overview'!$C$7 -> #DIV/0!
D18: Closing / Acquisition Costs: | E18: =H28 -> 0 | G18: Title Insurance: | H18: 0 | I18: =H18/'Financing Overview'!$C$7 -> #DIV/0!
D19: Rents Pro-Rating: | E19: 0 | G19: Legal: | H19: 0 | I19: =H19/'Financing Overview'!$C$7 -> #DIV/0!
D20: Deposit Last Month Rent: | E20: =-('Income and Expense Statement'!F23/12) -> 0 | G20: Corporation: | H20: 0 | I20: =H20/'Financing Overview'!$C$7 -> #DIV/0!
D21: Others: | E21: 0 | H21: 0 | I21: =H21/'Financing Overview'!$C$7 -> #DIV/0!
D22: Others: | E22: 0 | G22: Repairs: | H22: 0 | I22: =H22/'Financing Overview'!$C$7 -> #DIV/0!
D23: Others: | E23: 0 | H23: 0 | I23: =H23/'Financing Overview'!$C$7 -> #DIV/0!
D24: Others: | E24: 0 | G24: Assignment Fee: | H24: 0 | I24: =H24/'Financing Overview'!$C$7 -> #DIV/0!
D25: Others: | E25: 0 | G25: Others: | H25: 0 | I25: =H25/'Financing Overview'!$C$7 -> #DIV/0!
D26: Others: | E26: 0 | G26: Land Transfer Tax: | H26: =IF('Financing Overview'!C9<=55000,('Financing Overview'!C9*0.005),(IF('Financing Overview'!C9<=250000,((('Financing Overview'!C9-55000)*0.01)+275),(IF('Financing Overview'!C9>250000,((('Financing Overview'!C9-250000)*0.015)+2225),"check"))))) -> 0 | I26: =H26/'Financing Overview'!$C$7 -> #DIV/0!
C28: Total Cash Invested: | E28: =SUM(E16:E27) -> 0 | G28: Total Closing/ Acquisition Costs | H28: =SUM(H8:H26) -> 0 | I28: =SUM(I8:I26) -> #DIV/0!
